AUTHORS
LICENSE
MANIFEST.in
README.rst
setup.cfg
setup.py
test_app/__init__.py
test_app/manage.py
test_app/models.py
test_app/settings.py
test_app/wsgi.py
tests/conftest.py
tests/test_add_field.py
tests/test_add_unique.py
tests/test_create_index.py
tests/test_schema.py
zero_downtime_migrations/__init__.py
zero_downtime_migrations.egg-info/PKG-INFO
zero_downtime_migrations.egg-info/SOURCES.txt
zero_downtime_migrations.egg-info/dependency_links.txt
zero_downtime_migrations.egg-info/requires.txt
zero_downtime_migrations.egg-info/top_level.txt
zero_downtime_migrations/backend/__init__.py
zero_downtime_migrations/backend/base.py
zero_downtime_migrations/backend/exceptions.py
zero_downtime_migrations/backend/schema.py
zero_downtime_migrations/backend/sql_template.py