Metadata-Version: 1.2
Name: zero-downtime-migrations
Version: 0.12
Summary: django migrations without long locks
Home-page: https://github.com/yandex/zero-downtime-migrations
Author: Vladimir Koljasinskij
Author-email: smosker@yandex-team.ru
License: BSD-3-Clause
Keywords: django postgresql migrations
Platform: UNKNOWN
Classifier: Development Status :: 4 - Beta
Classifier: Framework :: Django
Classifier: Framework :: Django :: 1.8
Classifier: Framework :: Django :: 1.9
Classifier: Framework :: Django :: 1.10
Classifier: Framework :: Django :: 1.11
Classifier: Framework :: Django :: 2.0
Classifier: Framework :: Django :: 2.1
Classifier: Intended Audience :: Developers
Classifier: License :: OSI Approved :: BSD License
Classifier: Operating System :: OS Independent
Classifier: Topic :: Software Development :: Libraries :: Python Modules
Classifier: Programming Language :: Python
Classifier: Programming Language :: Python :: 2.7
Classifier: Programming Language :: Python :: 3.4
Classifier: Programming Language :: Python :: 3.5
Classifier: Programming Language :: Python :: 3.6
Requires-Python: >=2.7,!=3.1.*,!=3.0.*,!=3.2.*,!=3.3.*,<4.0
